<?xml version="1.0" encoding="utf-8" ?>
<dwsync>
<file name="DSC_0078.JPG" server="rss50.ymc.ne.jp" local="132285637290240877" remote="132460138800000000" Dst="0" />
<file name="DSC_0081.JPG" server="rss50.ymc.ne.jp" local="132285637208996804" remote="132460139400000000" Dst="0" />
<file name="DSC_0083.JPG" server="rss50.ymc.ne.jp" local="132285637263043390" remote="132460139400000000" Dst="0" />
<file name="DSC_0084.JPG" server="rss50.ymc.ne.jp" local="132285637221052171" remote="132460139400000000" Dst="0" />
<file name="tatsumi1.JPG" server="rss50.ymc.ne.jp" local="132285637322647834" remote="132460139400000000" Dst="0" />
<file name="tatsumi2.JPG" server="rss50.ymc.ne.jp" local="132285637305553378" remote="132460139400000000" Dst="0" />
<file name="tatsumi3.JPG" server="rss50.ymc.ne.jp" local="132285637237782344" remote="132460139400000000" Dst="0" />
<file name="tatsumi4.JPG" server="rss50.ymc.ne.jp" local="132285637272877951" remote="132460139400000000" Dst="0" />
<file name="tatsumiflyer.JPG" server="rss50.ymc.ne.jp" local="132292263103867836" remote="132460139400000000" Dst="0" />
<file name="tatsumimap.JPG" server="rss50.ymc.ne.jp" local="132292261273676800" remote="132460139400000000" Dst="0" />
</dwsync>